{
  "culture": "ru",
  "texts": {
    "AIModels": "AI модели",
    "Menu:AIModels": "AI модели",
    "Menu:AIModelsList": "Список моделей",
    "Table:Name": "Название",
    "Table:Vendor": "Вендор",
    "Table:Actions": "Операции",
    "AppName": "MergeSensei",
    "CreateProject:Name": "Название",
    "CreateProject:Description": "Описание",
    "CreateProject:GitToken": "Git токен доступа",
    "CreateProject:TitleEdit": "Редактирование проекта",
    "CreateProject:TitleAdd": "Создать новый проект",
    "Menu:My projects": "Мои проекты",
    "Menu:ContactUs": "Связаться с нами",
    "Menu:ArticleSample": "Образец статьи",
    "Menu:ListProjects": "Список проектов",
    "Menu:Projects": "Проекты",
    "MyProjects:Title": "Мои проекты",
    "MyProjects:StubTitle": "У вас пока нет проектов.",
    "MyProjects:StubSubtitle": "Начните с создания своего первого проекта, чтобы настроить автоматические проверки кода.",
    "MyProjects:ErrorStub": "Не удалось загрузить проекты. Пожалуйста, попробуйте еще раз", 
    "Button:CreateProject": "Создать проект",
    "Button:CreateNewProject": "Создать первый проект",
    "Button:Retry": "Попробовать снова",
    "Button:Edit": "Редактировать",
    "Button:AddRepository": "Новый репозиторий",
    "Button:AddNewRepository": "Добавить новый репозиторий",
    "ProductCard:Processes": "Процессов:",
    "ProductCard:LastLaunch": "Последний запуск:",
    "ProductCard:NoRepositories": "Репозитории не найдены",
    "Repositories:Stub": "Добавьте репозитории чтобы приступить к дальнейшим настройкам",
    "Repositories:ErrorStub": "Не удалось загрузить репозитории. Пожалуйста, попробуйте еще раз",
    "Toast:Success:CreateProject": "Проект успешно создан",
    "Toast:Success:UpdateProject": "Проект успешно обновлен",
    "Toast:success:DefaultTitle": "Успешно",
    "Toast:error:DefaultTitle": "Неуспешно",
    "Toast:Error:CreateProject": "Не удалось создать проект",
    "Toast:Error:UpdateProject": "Ошибка редактирования проекта",
    "Toast:Error:GetProjectsList": "Не удалось загрузить список проектов",
    "Toast:Error:GetRepositoriesList": "Не удалось загрузить список репозиториев",
    "Toast:Error:GetPipelinesList": "Не удалось загрузить список пайплайнов",
    "Table:Field:IsActive": "Активен", 
    "Table:Field:Repositories": "Репозитории",
    "Table:Field:Name": "Имя",
    "Table:Field:Url": "Url",
    "Table:Field:WebhookUrl": "Webhook url",
    "Table:Field:ProjectId": "Id проекта",
    "Home": "Дома",
    "Welcome": "Добро пожаловать",
    "LongWelcomeMessage": "Добро пожаловать в приложение. Это стартап-проект, основанный на структуре ABP. Для получения дополнительной информации посетите сайт",
    "Date": "датировать",
    "Permission:Dashboard": "Панель приборов",
    "Menu:Dashboard": "Панель приборов",
    "Menu:HomePage": "Домашняя страница",
    "Dashboard": "Панель приборов",
    "ExternalProvider:Google": "Google",
    "ExternalProvider:Google:ClientId": "ID клиента",
    "ExternalProvider:Google:ClientSecret": "Секрет клиента",
    "ExternalProvider:Microsoft": "Майкрософт",
    "ExternalProvider:Microsoft:ClientId": "ID клиента",
    "ExternalProvider:Microsoft:ClientSecret": "Секрет клиента",
    "ExternalProvider:Twitter": "Твиттер",
    "ExternalProvider:Twitter:ConsumerKey": "Потребительский ключ",
    "ExternalProvider:Twitter:ConsumerSecret": "Потребительский секрет",
    "NewsletterHeader": "Подпишитесь на рассылку!",
    "NewsletterInfo": "Получайте информацию о последних событиях.",
    "NewsletterPreference_Default": "Информационный бюллетень по умолчанию",
    "NewsletterPrivacyAcceptMessage": "Я принимаю <a href='/privacy-policy'>Политику конфиденциальности</a>.",
    "Language": "Язык",
    "Search": "Поиск",
    "LoadMore": "Загрузи больше",
    "Settings": "Настройки",
    "Theme": "Тема",
    "DeviceTheme": "Тема устройства",
    "Dark": "Темный",
    "Light": "Свет",
    "Unspecified": "Система",
    "SeeAllUsers": "Просмотреть всех пользователей",
    "TakePhoto": "Сделать фотографию",
    "ChoosePhoto": "Выбрать фото"
  }
}
